{
  "name": "ibm-resource-groups-terraform",
  "description": "Terraform configuration for creating multiple IBM Cloud Resource Groups in bulk",
  "type": [
    "terraform_v1.3"
  ],
  "location": "us-south",
  "resource_group": "default",
  "tags": [
    "terraform",
    "resource-groups",
    "ibm-cloud",
    "schematics"
  ],
  "template_repo": {
    "url": "https://github.com/your-org/ibm-resource-groups-terraform"
  },
  "template_data": [
    {
      "folder": ".",
      "type": "terraform_v1.3",
      "variablestore": [
        {
          "name": "ibmcloud_api_key",
          "type": "string",
          "secure": true,
          "description": "IBM Cloud API Key for authentication"
        },
        {
          "name": "region",
          "type": "string",
          "value": "us-south",
          "description": "IBM Cloud region"
        },
        {
          "name": "resource_groups",
          "type": "list(object({ name = string, tags = list(string) }))",
          "value": "[\n  {\n    name = \"powervs\",\n    tags = [\"environment:powervs\"]\n  },\n  {\n    name = \"vpc\",\n    tags = [\"environment:vpc\"]\n  },\n  {\n    name = \"cos\",\n    tags = [\"environment:cos\"]\n  },\n  {\n    name = \"log\",\n    tags = [\"environment:log\"]\n  }\n]",
          "description": "List of resource groups to create"
        }
      ]
    }
  ]
}